LICENSE
MANIFEST.in
README.rst
setup.py
django_speach_synthesizer/__init__.py
django_speach_synthesizer/admin.py
django_speach_synthesizer/apps.py
django_speach_synthesizer/models.py
django_speach_synthesizer/required.settings.py
django_speach_synthesizer/serializers.py
django_speach_synthesizer/tests.py
django_speach_synthesizer/urls.py
django_speach_synthesizer/views.py
django_speach_synthesizer.egg-info/PKG-INFO
django_speach_synthesizer.egg-info/SOURCES.txt
django_speach_synthesizer.egg-info/dependency_links.txt
django_speach_synthesizer.egg-info/requires.txt
django_speach_synthesizer.egg-info/top_level.txt
django_speach_synthesizer/management/__init__.py
django_speach_synthesizer/management/commands/__init__.py
django_speach_synthesizer/management/commands/clean_sound.py
django_speach_synthesizer/migrations/0001_initial.py
django_speach_synthesizer/migrations/__init__.py
django_speach_synthesizer/tests/__init__.py
django_speach_synthesizer/tests/test_views.py